ip_command/__init__.py
ip_command/ip.py
ip_command/model.py
ip_command/subcommands/__init__.py
ip_command/subcommands/addr.py
ip_command/subcommands/neigh.py
tests/__init__.py
tests/test.py
py_ip_command-0.0.3.dist-info/LICENSE
py_ip_command-0.0.3.dist-info/METADATA
py_ip_command-0.0.3.dist-info/WHEEL
py_ip_command-0.0.3.dist-info/top_level.txt
py_ip_command-0.0.3.dist-info/RECORD
