Metadata-Version: 2.1
Name: py-ip-command
Version: 0.0.3
Summary: A wrapper around the linux `ip` command
Home-page: https://github.com/Corvan/py-ip-command
Author: Lars Liedtke
Author-email: LarsLiedtke@gmx.de
License: LGPL v. 3.0
Platform: UNKNOWN
Classifier: Programming Language :: Python :: 3.7
Classifier: License :: OSI Approved :: GNU Lesser General Public License v3 (LGPLv3)
Classifier: Operating System :: POSIX :: Linux
Classifier: Topic :: Software Development :: Libraries :: Python Modules
Classifier: Topic :: Utilities
